{
	"list":[
		  {
		    "author": "kk11111", 
		    "date": "2015年9月20日", 
		    "content":"如何通过下面的JSON数据，动态生成博客的文章列表。（网页中的class都相同）。能用jquery吗？图片是例子，但需求相同。", 
		    "title": "微信页面整合WebApi111"
		  },  {
		    "author": "kk22222", 
		    "date": "2015年9月20日", 
		    "content":"如何通过下面的JSON数据，动态生成博客的文章列表。（网页中的class都相同）。能用jquery吗？图片是例子，但需求相同。", 
		    "title": "微信页面整合WebApi2222"
		  }, {
		    "author": "kk3333", 
		    "date": "2015年9月20日", 
		    "content":"如何通过下面的JSON数据，动态生成博客的文章列表。（网页中的class都相同）。能用jquery吗？图片是例子，但需求相同。", 
		    "title": "微信页面整合WebApi3333"
		  }, {
		    "author": "kk4444", 
		    "date": "2015年9月20日", 
		    "content":"如何通过下面的JSON数据，动态生成博客的文章列表。（网页中的class都相同）。能用jquery吗？图片是例子，但需求相同。", 
		    "title": "微信页面整合WebApi4444"
		  }
	]
}